raiseup/__init__.py
raiseup/posix.py
raiseup/windows.py
raiseup-0.2.dist-info/LICENSE
raiseup-0.2.dist-info/METADATA
raiseup-0.2.dist-info/WHEEL
raiseup-0.2.dist-info/top_level.txt
raiseup-0.2.dist-info/RECORD
