Metadata-Version: 2.1
Name: raiseup
Version: 0.2
Summary: Python library for requesting root privileges
Home-page: https://github.com/XploreInfinity/raiseup
Author: Barney Gale and XploreInfinity
License: MIT
Project-URL: Bug Tracker, https://github.com/XploreInfinity/raiseup/issues
Classifier: Programming Language :: Python :: 3
Classifier: License :: OSI Approved :: MIT License
Classifier: Operating System :: POSIX :: Linux
Classifier: Operating System :: Microsoft :: Windows
Classifier: Operating System :: MacOS :: MacOS X
Classifier: Operating System :: POSIX :: BSD :: FreeBSD
License-File: LICENSE
